cis221/Ch4/LabExerciseTwo/results/design.sv
// Code your design here
module LabExerciseTwo(a, b, c, G, H, I );
  input a, b, c;
  output G, H, I;
  
  assign G = a;					//G = x
  assign H = ~a & b | a & ~b;	//H = x’y + xy’
  assign I = ~b & c | b & ~c;	//I = y’z + yz’
  
endmodule

cis221/Ch4/LabExerciseTwo/results/testbench.sv
// Code your testbench here
// or browse Examples
module LabExerciseTwo_tb;
  reg a, b, c;
  wire G, H, I;
  
  LabExerciseTwo l2(.a(a),.b(b),.c(c),.G(G),.H(H),.I(I));
  initial begin
    $dumpfile("dump.vcd");
    $dumpvars(1);
    a=0; b=0; c=0;
    #1 
    //$display("a:%b,b:%b,c:%b ->  G:%b,H:%b,I:%b ",a,b,c,G,H,I);
    if (G == 0 & H== 0 & I== 0) $display("%b%b%b passed", a,b,c); else $error("%b%b%b failed", a,b,c);
   
    a=0; b=0; c=1;
    #1 
    //$display("a:%b,b:%b,c:%b ->  G:%b,H:%b,I:%b ",a,b,c,G,H,I);
    if (G == 0 & H== 0 & I== 1) $display("%b%b%b passed", a,b,c); else $error("%b%b%b failed", a,b,c);
    
    a=0; b=1; c=0;
    #1 
    //$display("a:%b,b:%b,c:%b ->  G:%b,H:%b,I:%b ",a,b,c,G,H,I);
    if (G == 0 & H== 1 & I== 1) $display("%b%b%b passed", a,b,c); else $error("%b%b%b failed", a,b,c);
   
    a=0; b=1; c=1;
    #1 
    //$display("a:%b,b:%b,c:%b ->  G:%b,H:%b,I:%b ",a,b,c,G,H,I);
    if (G == 0 & H== 1 & I== 0) $display("%b%b%b passed", a,b,c); else $error("%b%b%b failed", a,b,c);
    
    a=1; b=0; c=0;
    #1
    //$display("a:%b,b:%b,c:%b ->  G:%b,H:%b,I:%b ",a,b,c,G,H,I);
    if (G == 1 & H== 1 & I== 0) $display("%b%b%b passed", a,b,c); else $error("%b%b%b failed", a,b,c);
    
    a=1; b=0; c=1;
    #1
    //$display("a:%b,b:%b,c:%b ->  G:%b,H:%b,I:%b ",a,b,c,G,H,I);
    if (G == 1 & H== 1 & I== 1) $display("%b%b%b passed", a,b,c); else $error("%b%b%b failed", a,b,c);
    
    a=1; b=1; c=0;
    #1
    //$display("a:%b,b:%b,c:%b ->  G:%b,H:%b,I:%b ",a,b,c,G,H,I);
    if (G == 1 & H== 0 & I== 1) $display("%b%b%b passed", a,b,c); else $error("%b%b%b failed", a,b,c);
        
    a=1; b=1; c=1;
    #1
    //$display("a:%b,b:%b,c:%b ->  G:%b,H:%b,I:%b ",a,b,c,G,H,I);
    if (G == 1 & H== 0 & I== 0) $display("%b%b%b passed", a,b,c); else $error("%b%b%b failed", a,b,c);
    
  end

endmodule

cis221/Ch4/LabExerciseTwo/results/dump.vcd
$date
	Fri Oct 20 03:38:05 2023
$end
$version
	Icarus Verilog
$end
$timescale
	1s
$end
$scope module LabExerciseTwo_tb $end
$var wire 1 ! G $end
$var wire 1 " H $end
$var wire 1 # I $end
$var reg 1 $ a $end
$var reg 1 % b $end
$var reg 1 & c $end
$upscope $end
$enddefinitions $end
#0
$dumpvars
0&
0%
0$
0#
0"
0!
$end
#1
1#
1&
#2
1"
0&
1%
#3
0#
1&
#4
0&
0%
1$
1!
#5
1#
1&
#6
0"
0&
1%
#7
0#
1&
